database_handler/ConfigParser.py
database_handler/DatabaseHandler.py
database_handler/__init__.py
google_drive/__init__.py
google_drive/build_service.py
google_drive/worker.py
helper_scripts-0.4.3.dist-info/licenses/LICENSE
send_mail/ConfigParser.py
send_mail/SendMail.py
send_mail/__init__.py
helper_scripts-0.4.3.dist-info/METADATA
helper_scripts-0.4.3.dist-info/WHEEL
helper_scripts-0.4.3.dist-info/top_level.txt
helper_scripts-0.4.3.dist-info/RECORD
