Metadata-Version: 2.4
Name: helper_scripts
Version: 0.4.3
Summary: Database Helper Package
Home-page: https://github.com/winston1o1/helper-scripts
Author: Samuel Kizza & Winston Ssentongo
Author-email: Winston David Ssentongo <winstondavid96@gmail.com>, Samuel Kizza <SK8@gmail.com>
Maintainer: Winston David Ssentongo
Maintainer-email: Winston David Ssentongo <winstondavid96@gmail.com>
License: MIT License
Project-URL: homepage, https://github.com/winston1o1/helper-scripts.git
Classifier: Programming Language :: Python :: 3
Classifier: License :: OSI Approved :: MIT License
Classifier: Operating System :: OS Independent
Requires-Python: >=3.5
License-File: LICENSE
Requires-Dist: psycopg2
Requires-Dist: google-api-python-client
Dynamic: author
Dynamic: home-page
Dynamic: license-file
Dynamic: maintainer
